async_fastapi_jwt_auth/__init__.py
async_fastapi_jwt_auth/auth_config.py
async_fastapi_jwt_auth/auth_jwt.py
async_fastapi_jwt_auth/config.py
async_fastapi_jwt_auth/exceptions.py
async_fastapi_jwt_auth-0.6.6.dist-info/LICENSE
async_fastapi_jwt_auth-0.6.6.dist-info/METADATA
async_fastapi_jwt_auth-0.6.6.dist-info/WHEEL
async_fastapi_jwt_auth-0.6.6.dist-info/RECORD
