Metadata-Version: 2.1
Name: async-fastapi-jwt-auth
Version: 0.6.6
Summary: Async fork of FastAPI extension that provides JWT Auth support (secure, easy to use and lightweight)
License: MIT
Author: Yan Khachko
Author-email: a@slnk.icu
Requires-Python: >=3.8
Classifier: Environment :: Web Environment
Classifier: Intended Audience :: Developers
Classifier: License :: OSI Approved :: MIT License
Classifier: Operating System :: OS Independent
Classifier: Programming Language :: Python :: 3
Classifier: Programming Language :: Python :: 3.8
Classifier: Programming Language :: Python :: 3.9
Classifier: Programming Language :: Python :: 3.10
Classifier: Programming Language :: Python :: 3.11
Classifier: Programming Language :: Python :: 3.10
Classifier: Programming Language :: Python :: 3.11
Classifier: Programming Language :: Python :: 3.12
Classifier: Programming Language :: Python :: 3.8
Classifier: Programming Language :: Python :: 3.9
Classifier: Topic :: Internet :: WWW/HTTP :: Dynamic Content
Classifier: Topic :: Software Development :: Libraries :: Python Modules
Provides-Extra: asymmetric
Requires-Dist: PyJWT (>=2.8.0)
Requires-Dist: cryptography (>=42.0.5) ; extra == "asymmetric"
Requires-Dist: fastapi (>=0.109.0)
Requires-Dist: httpx (>=0.23.3)
Requires-Dist: pydantic-settings (>=2.2.1)
Project-URL: Documentation, https://sijokun.github.io/async-fastapi-jwt-auth
Project-URL: Source, https://github.com/sijokun/async-fastapi-jwt-auth
